{
  "filename": "bstojkovic___youtube-downloader.json",
  "id": 87858873,
  "name": "youtube-downloader",
  "fullName": "bstojkovic/youtube-downloader",
  "owner": {
    "login": "bstojkovic",
    "id": 26883538,
    "avatarUrl": "https://avatars0.githubusercontent.com/u/26883538?v=3",
    "gravatarId": "",
    "url": "https://api.github.com/users/bstojkovic",
    "htmlUrl": "https://github.com/bstojkovic",
    "followersUrl": "https://api.github.com/users/bstojkovic/followers",
    "subscriptionsUrl": "https://api.github.com/users/bstojkovic/subscriptions",
    "organizationsUrl": "https://api.github.com/users/bstojkovic/orgs",
    "reposUrl": "https://api.github.com/users/bstojkovic/repos",
    "receivedEventsUrl": "https://api.github.com/users/bstojkovic/received_events",
    "type": "User"
  },
  "private": false,
  "htmlUrl": "https://github.com/bstojkovic/youtube-downloader",
  "description": "A youtube downloader",
  "fork": false,
  "url": "https://api.github.com/repos/bstojkovic/youtube-downloader",
  "forksUrl": "https://api.github.com/repos/bstojkovic/youtube-downloader/forks",
  "teamsUrl": "https://api.github.com/repos/bstojkovic/youtube-downloader/teams",
  "hooksUrl": "https://api.github.com/repos/bstojkovic/youtube-downloader/hooks",
  "eventsUrl": "https://api.github.com/repos/bstojkovic/youtube-downloader/events",
  "tagsUrl": "https://api.github.com/repos/bstojkovic/youtube-downloader/tags",
  "languagesUrl": "https://api.github.com/repos/bstojkovic/youtube-downloader/languages",
  "stargazersUrl": "https://api.github.com/repos/bstojkovic/youtube-downloader/stargazers",
  "contributorsUrl": "https://api.github.com/repos/bstojkovic/youtube-downloader/contributors",
  "subscribersUrl": "https://api.github.com/repos/bstojkovic/youtube-downloader/subscribers",
  "subscriptionUrl": "https://api.github.com/repos/bstojkovic/youtube-downloader/subscription",
  "mergesUrl": "https://api.github.com/repos/bstojkovic/youtube-downloader/merges",
  "downloadsUrl": "https://api.github.com/repos/bstojkovic/youtube-downloader/downloads",
  "deploymentsUrl": "https://api.github.com/repos/bstojkovic/youtube-downloader/deployments",
  "createdAt": "2017-04-10T21:22:13.000Z",
  "updatedAt": "2017-04-24T20:09:43.000Z",
  "pushedAt": "2017-04-21T15:02:23.000Z",
  "gitUrl": "git://github.com/bstojkovic/youtube-downloader.git",
  "sshUrl": "git@github.com:bstojkovic/youtube-downloader.git",
  "cloneUrl": "https://github.com/bstojkovic/youtube-downloader.git",
  "svnUrl": "https://github.com/bstojkovic/youtube-downloader",
  "homepage": "",
  "size": 62,
  "stargazersCount": 2,
  "watchersCount": 2,
  "language": "HTML",
  "hasIssues": true,
  "hasProjects": true,
  "hasDownloads": true,
  "hasWiki": true,
  "hasPages": false,
  "forksCount": 0,
  "mirrorUrl": null,
  "openIssuesCount": 0,
  "openIssues": 0,
  "watchers": 2,
  "defaultBranch": "master",
  "permissions": {
    "admin": false,
    "push": false,
    "pull": true
  },
  "license": {
    "key": "cc0-1.0",
    "name": "Creative Commons Zero v1.0 Universal",
    "spdxId": "CC0-1.0",
    "url": "https://api.github.com/licenses/cc0-1.0",
    "featured": false
  },
  "networkCount": 0,
  "subscribersCount": 0,
  "status": 200,
  "lastFetchedAt": "2017-05-04T20:32:11.804Z",
  "packageJSON": {
    "name": "youtube-downloader",
    "productName": "Youtube Downloader",
    "version": "0.0.2",
    "description": "Youtube Downloader",
    "main": "main.js",
    "scripts": {
      "start": "electron ."
    },
    "repository": "",
    "keywords": [],
    "author": "Bozo Stojkovic",
    "license": "",
    "devDependencies": {
      "electron": "~1.6.2",
      "electron-packager": "^8.6.0"
    },
    "dependencies": {
      "electron-debug": "^1.1.0",
      "request-promise": "^4.2.0",
      "ytdl-core": "^0.12.1"
    }
  },
  "packageStatus": 200,
  "packageLastFetchedAt": "2017-05-04T22:36:46.140Z"
}