{
  "filename": "ByronKos___SE300-Journal.json",
  "id": 80462854,
  "name": "SE300-Journal",
  "fullName": "ByronKos/SE300-Journal",
  "owner": {
    "login": "ByronKos",
    "id": 11277387,
    "avatarUrl": "https://avatars2.githubusercontent.com/u/11277387?v=4",
    "gravatarId": "",
    "url": "https://api.github.com/users/ByronKos",
    "htmlUrl": "https://github.com/ByronKos",
    "followersUrl": "https://api.github.com/users/ByronKos/followers",
    "subscriptionsUrl": "https://api.github.com/users/ByronKos/subscriptions",
    "organizationsUrl": "https://api.github.com/users/ByronKos/orgs",
    "reposUrl": "https://api.github.com/users/ByronKos/repos",
    "receivedEventsUrl": "https://api.github.com/users/ByronKos/received_events",
    "type": "User"
  },
  "private": false,
  "htmlUrl": "https://github.com/ByronKos/SE300-Journal",
  "description": null,
  "fork": false,
  "url": "https://api.github.com/repos/ByronKos/SE300-Journal",
  "forksUrl": "https://api.github.com/repos/ByronKos/SE300-Journal/forks",
  "teamsUrl": "https://api.github.com/repos/ByronKos/SE300-Journal/teams",
  "hooksUrl": "https://api.github.com/repos/ByronKos/SE300-Journal/hooks",
  "eventsUrl": "https://api.github.com/repos/ByronKos/SE300-Journal/events",
  "tagsUrl": "https://api.github.com/repos/ByronKos/SE300-Journal/tags",
  "languagesUrl": "https://api.github.com/repos/ByronKos/SE300-Journal/languages",
  "stargazersUrl": "https://api.github.com/repos/ByronKos/SE300-Journal/stargazers",
  "contributorsUrl": "https://api.github.com/repos/ByronKos/SE300-Journal/contributors",
  "subscribersUrl": "https://api.github.com/repos/ByronKos/SE300-Journal/subscribers",
  "subscriptionUrl": "https://api.github.com/repos/ByronKos/SE300-Journal/subscription",
  "mergesUrl": "https://api.github.com/repos/ByronKos/SE300-Journal/merges",
  "downloadsUrl": "https://api.github.com/repos/ByronKos/SE300-Journal/downloads",
  "deploymentsUrl": "https://api.github.com/repos/ByronKos/SE300-Journal/deployments",
  "createdAt": "2017-01-30T20:57:50.000Z",
  "updatedAt": "2017-04-05T19:17:51.000Z",
  "pushedAt": "2017-05-01T17:38:18.000Z",
  "gitUrl": "git://github.com/ByronKos/SE300-Journal.git",
  "sshUrl": "git@github.com:ByronKos/SE300-Journal.git",
  "cloneUrl": "https://github.com/ByronKos/SE300-Journal.git",
  "svnUrl": "https://github.com/ByronKos/SE300-Journal",
  "homepage": null,
  "size": 2984,
  "stargazersCount": 4,
  "watchersCount": 4,
  "language": "JavaScript",
  "hasIssues": true,
  "hasProjects": true,
  "hasDownloads": true,
  "hasWiki": true,
  "hasPages": true,
  "forksCount": 0,
  "mirrorUrl": null,
  "archived": false,
  "openIssuesCount": 0,
  "openIssues": 0,
  "watchers": 4,
  "defaultBranch": "master",
  "permissions": {
    "admin": false,
    "push": false,
    "pull": true
  },
  "license": {
    "key": "mit",
    "name": "MIT License",
    "spdxId": "MIT",
    "url": "https://api.github.com/licenses/mit",
    "featured": true
  },
  "networkCount": 0,
  "subscribersCount": 2,
  "status": 200,
  "lastFetchedAt": "2017-10-23T22:31:14.010Z"
}