{
  "filename": "djalmaaraujo___spotifube.json",
  "id": 106751697,
  "name": "spotifube",
  "fullName": "djalmaaraujo/spotifube",
  "owner": {
    "login": "djalmaaraujo",
    "id": 3402,
    "avatarUrl": "https://avatars1.githubusercontent.com/u/3402?v=4",
    "gravatarId": "",
    "url": "https://api.github.com/users/djalmaaraujo",
    "htmlUrl": "https://github.com/djalmaaraujo",
    "followersUrl": "https://api.github.com/users/djalmaaraujo/followers",
    "subscriptionsUrl": "https://api.github.com/users/djalmaaraujo/subscriptions",
    "organizationsUrl": "https://api.github.com/users/djalmaaraujo/orgs",
    "reposUrl": "https://api.github.com/users/djalmaaraujo/repos",
    "receivedEventsUrl": "https://api.github.com/users/djalmaaraujo/received_events",
    "type": "User"
  },
  "private": false,
  "htmlUrl": "https://github.com/djalmaaraujo/spotifube",
  "description": "Download songs from youtube using Spotify playlists. It's awesome.",
  "fork": false,
  "url": "https://api.github.com/repos/djalmaaraujo/spotifube",
  "forksUrl": "https://api.github.com/repos/djalmaaraujo/spotifube/forks",
  "teamsUrl": "https://api.github.com/repos/djalmaaraujo/spotifube/teams",
  "hooksUrl": "https://api.github.com/repos/djalmaaraujo/spotifube/hooks",
  "eventsUrl": "https://api.github.com/repos/djalmaaraujo/spotifube/events",
  "tagsUrl": "https://api.github.com/repos/djalmaaraujo/spotifube/tags",
  "languagesUrl": "https://api.github.com/repos/djalmaaraujo/spotifube/languages",
  "stargazersUrl": "https://api.github.com/repos/djalmaaraujo/spotifube/stargazers",
  "contributorsUrl": "https://api.github.com/repos/djalmaaraujo/spotifube/contributors",
  "subscribersUrl": "https://api.github.com/repos/djalmaaraujo/spotifube/subscribers",
  "subscriptionUrl": "https://api.github.com/repos/djalmaaraujo/spotifube/subscription",
  "mergesUrl": "https://api.github.com/repos/djalmaaraujo/spotifube/merges",
  "downloadsUrl": "https://api.github.com/repos/djalmaaraujo/spotifube/downloads",
  "deploymentsUrl": "https://api.github.com/repos/djalmaaraujo/spotifube/deployments",
  "createdAt": "2017-10-12T22:27:23.000Z",
  "updatedAt": "2017-10-19T05:36:14.000Z",
  "pushedAt": "2017-10-17T12:45:03.000Z",
  "gitUrl": "git://github.com/djalmaaraujo/spotifube.git",
  "sshUrl": "git@github.com:djalmaaraujo/spotifube.git",
  "cloneUrl": "https://github.com/djalmaaraujo/spotifube.git",
  "svnUrl": "https://github.com/djalmaaraujo/spotifube",
  "homepage": null,
  "size": 59,
  "stargazersCount": 3,
  "watchersCount": 3,
  "language": "JavaScript",
  "hasIssues": true,
  "hasProjects": true,
  "hasDownloads": true,
  "hasWiki": true,
  "hasPages": false,
  "forksCount": 0,
  "mirrorUrl": null,
  "archived": false,
  "openIssuesCount": 2,
  "openIssues": 2,
  "watchers": 3,
  "defaultBranch": "master",
  "permissions": {
    "admin": false,
    "push": false,
    "pull": true
  },
  "license": null,
  "networkCount": 0,
  "subscribersCount": 2,
  "status": 200,
  "lastFetchedAt": "2017-10-23T18:18:10.173Z"
}