{
  "filename": "hannahpatellis___scn-now.json",
  "id": 93803875,
  "name": "garden",
  "fullName": "hannahpatellis/garden",
  "owner": {
    "login": "hannahpatellis",
    "id": 22241247,
    "avatarUrl": "https://avatars2.githubusercontent.com/u/22241247?v=4",
    "gravatarId": "",
    "url": "https://api.github.com/users/hannahpatellis",
    "htmlUrl": "https://github.com/hannahpatellis",
    "followersUrl": "https://api.github.com/users/hannahpatellis/followers",
    "subscriptionsUrl": "https://api.github.com/users/hannahpatellis/subscriptions",
    "organizationsUrl": "https://api.github.com/users/hannahpatellis/orgs",
    "reposUrl": "https://api.github.com/users/hannahpatellis/repos",
    "receivedEventsUrl": "https://api.github.com/users/hannahpatellis/received_events",
    "type": "User"
  },
  "private": false,
  "htmlUrl": "https://github.com/hannahpatellis/garden",
  "description": "A garden of small apps and scripts (plants) all contained in a single, expandable, easy to use app",
  "fork": false,
  "url": "https://api.github.com/repos/hannahpatellis/garden",
  "forksUrl": "https://api.github.com/repos/hannahpatellis/garden/forks",
  "teamsUrl": "https://api.github.com/repos/hannahpatellis/garden/teams",
  "hooksUrl": "https://api.github.com/repos/hannahpatellis/garden/hooks",
  "eventsUrl": "https://api.github.com/repos/hannahpatellis/garden/events",
  "tagsUrl": "https://api.github.com/repos/hannahpatellis/garden/tags",
  "languagesUrl": "https://api.github.com/repos/hannahpatellis/garden/languages",
  "stargazersUrl": "https://api.github.com/repos/hannahpatellis/garden/stargazers",
  "contributorsUrl": "https://api.github.com/repos/hannahpatellis/garden/contributors",
  "subscribersUrl": "https://api.github.com/repos/hannahpatellis/garden/subscribers",
  "subscriptionUrl": "https://api.github.com/repos/hannahpatellis/garden/subscription",
  "mergesUrl": "https://api.github.com/repos/hannahpatellis/garden/merges",
  "downloadsUrl": "https://api.github.com/repos/hannahpatellis/garden/downloads",
  "deploymentsUrl": "https://api.github.com/repos/hannahpatellis/garden/deployments",
  "createdAt": "2017-06-09T00:47:51.000Z",
  "updatedAt": "2017-06-27T22:26:50.000Z",
  "pushedAt": "2017-07-14T21:31:36.000Z",
  "gitUrl": "git://github.com/hannahpatellis/garden.git",
  "sshUrl": "git@github.com:hannahpatellis/garden.git",
  "cloneUrl": "https://github.com/hannahpatellis/garden.git",
  "svnUrl": "https://github.com/hannahpatellis/garden",
  "homepage": "",
  "size": 3389,
  "stargazersCount": 0,
  "watchersCount": 0,
  "language": "HTML",
  "hasIssues": true,
  "hasProjects": true,
  "hasDownloads": true,
  "hasWiki": true,
  "hasPages": false,
  "forksCount": 0,
  "mirrorUrl": null,
  "archived": false,
  "openIssuesCount": 0,
  "openIssues": 0,
  "watchers": 0,
  "defaultBranch": "master",
  "permissions": {
    "admin": false,
    "push": false,
    "pull": true
  },
  "license": {
    "key": "gpl-3.0",
    "name": "GNU General Public License v3.0",
    "spdxId": "GPL-3.0",
    "url": "https://api.github.com/licenses/gpl-3.0",
    "featured": true
  },
  "networkCount": 0,
  "subscribersCount": 0,
  "status": 200,
  "lastFetchedAt": "2017-10-23T20:44:55.474Z"
}