{
  "filename": "Jayuda___devdoc.json",
  "id": 91856556,
  "name": "devdoc",
  "fullName": "Jayuda/devdoc",
  "owner": {
    "login": "Jayuda",
    "id": 1973447,
    "avatarUrl": "https://avatars2.githubusercontent.com/u/1973447?v=4",
    "gravatarId": "",
    "url": "https://api.github.com/users/Jayuda",
    "htmlUrl": "https://github.com/Jayuda",
    "followersUrl": "https://api.github.com/users/Jayuda/followers",
    "subscriptionsUrl": "https://api.github.com/users/Jayuda/subscriptions",
    "organizationsUrl": "https://api.github.com/users/Jayuda/orgs",
    "reposUrl": "https://api.github.com/users/Jayuda/repos",
    "receivedEventsUrl": "https://api.github.com/users/Jayuda/received_events",
    "type": "User"
  },
  "private": false,
  "htmlUrl": "https://github.com/Jayuda/devdoc",
  "description": "Electron app for https://devdocs.io/",
  "fork": false,
  "url": "https://api.github.com/repos/Jayuda/devdoc",
  "forksUrl": "https://api.github.com/repos/Jayuda/devdoc/forks",
  "teamsUrl": "https://api.github.com/repos/Jayuda/devdoc/teams",
  "hooksUrl": "https://api.github.com/repos/Jayuda/devdoc/hooks",
  "eventsUrl": "https://api.github.com/repos/Jayuda/devdoc/events",
  "tagsUrl": "https://api.github.com/repos/Jayuda/devdoc/tags",
  "languagesUrl": "https://api.github.com/repos/Jayuda/devdoc/languages",
  "stargazersUrl": "https://api.github.com/repos/Jayuda/devdoc/stargazers",
  "contributorsUrl": "https://api.github.com/repos/Jayuda/devdoc/contributors",
  "subscribersUrl": "https://api.github.com/repos/Jayuda/devdoc/subscribers",
  "subscriptionUrl": "https://api.github.com/repos/Jayuda/devdoc/subscription",
  "mergesUrl": "https://api.github.com/repos/Jayuda/devdoc/merges",
  "downloadsUrl": "https://api.github.com/repos/Jayuda/devdoc/downloads",
  "deploymentsUrl": "https://api.github.com/repos/Jayuda/devdoc/deployments",
  "createdAt": "2017-05-20T01:10:46.000Z",
  "updatedAt": "2017-05-20T01:17:46.000Z",
  "pushedAt": "2017-05-20T01:20:56.000Z",
  "gitUrl": "git://github.com/Jayuda/devdoc.git",
  "sshUrl": "git@github.com:Jayuda/devdoc.git",
  "cloneUrl": "https://github.com/Jayuda/devdoc.git",
  "svnUrl": "https://github.com/Jayuda/devdoc",
  "homepage": null,
  "size": 403,
  "stargazersCount": 0,
  "watchersCount": 0,
  "language": "CSS",
  "hasIssues": true,
  "hasProjects": true,
  "hasDownloads": true,
  "hasWiki": true,
  "hasPages": false,
  "forksCount": 0,
  "mirrorUrl": null,
  "archived": false,
  "openIssuesCount": 0,
  "openIssues": 0,
  "watchers": 0,
  "defaultBranch": "master",
  "permissions": {
    "admin": false,
    "push": false,
    "pull": true
  },
  "license": {
    "key": "cc0-1.0",
    "name": "Creative Commons Zero v1.0 Universal",
    "spdxId": "CC0-1.0",
    "url": "https://api.github.com/licenses/cc0-1.0",
    "featured": false
  },
  "networkCount": 0,
  "subscribersCount": 1,
  "status": 200,
  "lastFetchedAt": "2017-10-23T20:07:23.861Z"
}