{
  "filename": "juliangruber___preact-level-list.json",
  "id": 107021062,
  "name": "preact-level-list",
  "fullName": "juliangruber/preact-level-list",
  "owner": {
    "login": "juliangruber",
    "id": 10247,
    "avatarUrl": "https://avatars2.githubusercontent.com/u/10247?v=4",
    "gravatarId": "",
    "url": "https://api.github.com/users/juliangruber",
    "htmlUrl": "https://github.com/juliangruber",
    "followersUrl": "https://api.github.com/users/juliangruber/followers",
    "subscriptionsUrl": "https://api.github.com/users/juliangruber/subscriptions",
    "organizationsUrl": "https://api.github.com/users/juliangruber/orgs",
    "reposUrl": "https://api.github.com/users/juliangruber/repos",
    "receivedEventsUrl": "https://api.github.com/users/juliangruber/received_events",
    "type": "User"
  },
  "private": false,
  "htmlUrl": "https://github.com/juliangruber/preact-level-list",
  "description": "Live updating leveldb list component for preact",
  "fork": false,
  "url": "https://api.github.com/repos/juliangruber/preact-level-list",
  "forksUrl": "https://api.github.com/repos/juliangruber/preact-level-list/forks",
  "teamsUrl": "https://api.github.com/repos/juliangruber/preact-level-list/teams",
  "hooksUrl": "https://api.github.com/repos/juliangruber/preact-level-list/hooks",
  "eventsUrl": "https://api.github.com/repos/juliangruber/preact-level-list/events",
  "tagsUrl": "https://api.github.com/repos/juliangruber/preact-level-list/tags",
  "languagesUrl": "https://api.github.com/repos/juliangruber/preact-level-list/languages",
  "stargazersUrl": "https://api.github.com/repos/juliangruber/preact-level-list/stargazers",
  "contributorsUrl": "https://api.github.com/repos/juliangruber/preact-level-list/contributors",
  "subscribersUrl": "https://api.github.com/repos/juliangruber/preact-level-list/subscribers",
  "subscriptionUrl": "https://api.github.com/repos/juliangruber/preact-level-list/subscription",
  "mergesUrl": "https://api.github.com/repos/juliangruber/preact-level-list/merges",
  "downloadsUrl": "https://api.github.com/repos/juliangruber/preact-level-list/downloads",
  "deploymentsUrl": "https://api.github.com/repos/juliangruber/preact-level-list/deployments",
  "createdAt": "2017-10-15T14:46:50.000Z",
  "updatedAt": "2017-10-15T17:55:15.000Z",
  "pushedAt": "2017-10-15T14:47:57.000Z",
  "gitUrl": "git://github.com/juliangruber/preact-level-list.git",
  "sshUrl": "git@github.com:juliangruber/preact-level-list.git",
  "cloneUrl": "https://github.com/juliangruber/preact-level-list.git",
  "svnUrl": "https://github.com/juliangruber/preact-level-list",
  "homepage": null,
  "size": 237,
  "stargazersCount": 3,
  "watchersCount": 3,
  "language": "JavaScript",
  "hasIssues": true,
  "hasProjects": true,
  "hasDownloads": true,
  "hasWiki": true,
  "hasPages": false,
  "forksCount": 0,
  "mirrorUrl": null,
  "archived": false,
  "openIssuesCount": 0,
  "openIssues": 0,
  "watchers": 3,
  "defaultBranch": "master",
  "permissions": {
    "admin": false,
    "push": false,
    "pull": true
  },
  "license": null,
  "networkCount": 0,
  "subscribersCount": 1,
  "status": 200,
  "lastFetchedAt": "2017-10-23T22:32:48.021Z"
}