{
  "filename": "K3nny13___still_to_do.json",
  "id": 105939308,
  "name": "still_to_do",
  "fullName": "K3nny13/still_to_do",
  "owner": {
    "login": "K3nny13",
    "id": 10127413,
    "avatarUrl": "https://avatars0.githubusercontent.com/u/10127413?v=4",
    "gravatarId": "",
    "url": "https://api.github.com/users/K3nny13",
    "htmlUrl": "https://github.com/K3nny13",
    "followersUrl": "https://api.github.com/users/K3nny13/followers",
    "subscriptionsUrl": "https://api.github.com/users/K3nny13/subscriptions",
    "organizationsUrl": "https://api.github.com/users/K3nny13/orgs",
    "reposUrl": "https://api.github.com/users/K3nny13/repos",
    "receivedEventsUrl": "https://api.github.com/users/K3nny13/received_events",
    "type": "User"
  },
  "private": false,
  "htmlUrl": "https://github.com/K3nny13/still_to_do",
  "description": "testing electron",
  "fork": false,
  "url": "https://api.github.com/repos/K3nny13/still_to_do",
  "forksUrl": "https://api.github.com/repos/K3nny13/still_to_do/forks",
  "teamsUrl": "https://api.github.com/repos/K3nny13/still_to_do/teams",
  "hooksUrl": "https://api.github.com/repos/K3nny13/still_to_do/hooks",
  "eventsUrl": "https://api.github.com/repos/K3nny13/still_to_do/events",
  "tagsUrl": "https://api.github.com/repos/K3nny13/still_to_do/tags",
  "languagesUrl": "https://api.github.com/repos/K3nny13/still_to_do/languages",
  "stargazersUrl": "https://api.github.com/repos/K3nny13/still_to_do/stargazers",
  "contributorsUrl": "https://api.github.com/repos/K3nny13/still_to_do/contributors",
  "subscribersUrl": "https://api.github.com/repos/K3nny13/still_to_do/subscribers",
  "subscriptionUrl": "https://api.github.com/repos/K3nny13/still_to_do/subscription",
  "mergesUrl": "https://api.github.com/repos/K3nny13/still_to_do/merges",
  "downloadsUrl": "https://api.github.com/repos/K3nny13/still_to_do/downloads",
  "deploymentsUrl": "https://api.github.com/repos/K3nny13/still_to_do/deployments",
  "createdAt": "2017-10-05T20:52:59.000Z",
  "updatedAt": "2017-10-05T21:02:51.000Z",
  "pushedAt": "2017-10-07T09:00:17.000Z",
  "gitUrl": "git://github.com/K3nny13/still_to_do.git",
  "sshUrl": "git@github.com:K3nny13/still_to_do.git",
  "cloneUrl": "https://github.com/K3nny13/still_to_do.git",
  "svnUrl": "https://github.com/K3nny13/still_to_do",
  "homepage": null,
  "size": 5,
  "stargazersCount": 0,
  "watchersCount": 0,
  "language": "JavaScript",
  "hasIssues": true,
  "hasProjects": true,
  "hasDownloads": true,
  "hasWiki": true,
  "hasPages": false,
  "forksCount": 0,
  "mirrorUrl": null,
  "archived": false,
  "openIssuesCount": 0,
  "openIssues": 0,
  "watchers": 0,
  "defaultBranch": "master",
  "permissions": {
    "admin": false,
    "push": false,
    "pull": true
  },
  "license": {
    "key": "mit",
    "name": "MIT License",
    "spdxId": "MIT",
    "url": "https://api.github.com/licenses/mit",
    "featured": true
  },
  "networkCount": 0,
  "subscribersCount": 1,
  "status": 200,
  "lastFetchedAt": "2017-10-23T17:44:58.487Z"
}