{
  "filename": "nodety___electronic-wechat.json",
  "id": 79884811,
  "name": "electronic-wechat",
  "fullName": "nodety/electronic-wechat",
  "owner": {
    "login": "nodety",
    "id": 14356872,
    "avatarUrl": "https://avatars2.githubusercontent.com/u/14356872?v=3",
    "gravatarId": "",
    "url": "https://api.github.com/users/nodety",
    "htmlUrl": "https://github.com/nodety",
    "followersUrl": "https://api.github.com/users/nodety/followers",
    "subscriptionsUrl": "https://api.github.com/users/nodety/subscriptions",
    "organizationsUrl": "https://api.github.com/users/nodety/orgs",
    "reposUrl": "https://api.github.com/users/nodety/repos",
    "receivedEventsUrl": "https://api.github.com/users/nodety/received_events",
    "type": "Organization"
  },
  "private": false,
  "htmlUrl": "https://github.com/nodety/electronic-wechat",
  "description": ":speech_balloon: A better WeChat on macOS and Linux. Built with Electron by Zhongyi Tong.",
  "fork": true,
  "url": "https://api.github.com/repos/nodety/electronic-wechat",
  "forksUrl": "https://api.github.com/repos/nodety/electronic-wechat/forks",
  "teamsUrl": "https://api.github.com/repos/nodety/electronic-wechat/teams",
  "hooksUrl": "https://api.github.com/repos/nodety/electronic-wechat/hooks",
  "eventsUrl": "https://api.github.com/repos/nodety/electronic-wechat/events",
  "tagsUrl": "https://api.github.com/repos/nodety/electronic-wechat/tags",
  "languagesUrl": "https://api.github.com/repos/nodety/electronic-wechat/languages",
  "stargazersUrl": "https://api.github.com/repos/nodety/electronic-wechat/stargazers",
  "contributorsUrl": "https://api.github.com/repos/nodety/electronic-wechat/contributors",
  "subscribersUrl": "https://api.github.com/repos/nodety/electronic-wechat/subscribers",
  "subscriptionUrl": "https://api.github.com/repos/nodety/electronic-wechat/subscription",
  "mergesUrl": "https://api.github.com/repos/nodety/electronic-wechat/merges",
  "downloadsUrl": "https://api.github.com/repos/nodety/electronic-wechat/downloads",
  "deploymentsUrl": "https://api.github.com/repos/nodety/electronic-wechat/deployments",
  "createdAt": "2017-01-24T06:22:21.000Z",
  "updatedAt": "2017-01-24T06:22:24.000Z",
  "pushedAt": "2017-01-23T11:14:39.000Z",
  "gitUrl": "git://github.com/nodety/electronic-wechat.git",
  "sshUrl": "git@github.com:nodety/electronic-wechat.git",
  "cloneUrl": "https://github.com/nodety/electronic-wechat.git",
  "svnUrl": "https://github.com/nodety/electronic-wechat",
  "homepage": "",
  "size": 1067,
  "stargazersCount": 0,
  "watchersCount": 0,
  "language": "JavaScript",
  "hasIssues": false,
  "hasProjects": true,
  "hasDownloads": true,
  "hasWiki": true,
  "hasPages": false,
  "forksCount": 0,
  "mirrorUrl": null,
  "openIssuesCount": 0,
  "openIssues": 0,
  "watchers": 0,
  "defaultBranch": "master",
  "permissions": {
    "admin": false,
    "push": false,
    "pull": true
  },
  "license": null,
  "organization": {
    "login": "nodety",
    "id": 14356872,
    "avatarUrl": "https://avatars2.githubusercontent.com/u/14356872?v=3",
    "gravatarId": "",
    "url": "https://api.github.com/users/nodety",
    "htmlUrl": "https://github.com/nodety",
    "followersUrl": "https://api.github.com/users/nodety/followers",
    "subscriptionsUrl": "https://api.github.com/users/nodety/subscriptions",
    "organizationsUrl": "https://api.github.com/users/nodety/orgs",
    "reposUrl": "https://api.github.com/users/nodety/repos",
    "receivedEventsUrl": "https://api.github.com/users/nodety/received_events",
    "type": "Organization"
  },
  "parent": {
    "id": 51994692,
    "name": "electronic-wechat",
    "fullName": "geeeeeeeeek/electronic-wechat",
    "owner": {
      "login": "geeeeeeeeek",
      "id": 7262715,
      "avatarUrl": "https://avatars2.githubusercontent.com/u/7262715?v=3",
      "gravatarId": "",
      "url": "https://api.github.com/users/geeeeeeeeek",
      "htmlUrl": "https://github.com/geeeeeeeeek",
      "followersUrl": "https://api.github.com/users/geeeeeeeeek/followers",
      "subscriptionsUrl": "https://api.github.com/users/geeeeeeeeek/subscriptions",
      "organizationsUrl": "https://api.github.com/users/geeeeeeeeek/orgs",
      "reposUrl": "https://api.github.com/users/geeeeeeeeek/repos",
      "receivedEventsUrl": "https://api.github.com/users/geeeeeeeeek/received_events",
      "type": "User"
    },
    "private": false,
    "htmlUrl": "https://github.com/geeeeeeeeek/electronic-wechat",
    "description": ":speech_balloon: A better WeChat on macOS and Linux. Built with Electron by Zhongyi Tong.",
    "fork": false,
    "url": "https://api.github.com/repos/geeeeeeeeek/electronic-wechat",
    "forksUrl": "https://api.github.com/repos/geeeeeeeeek/electronic-wechat/forks",
    "teamsUrl": "https://api.github.com/repos/geeeeeeeeek/electronic-wechat/teams",
    "hooksUrl": "https://api.github.com/repos/geeeeeeeeek/electronic-wechat/hooks",
    "eventsUrl": "https://api.github.com/repos/geeeeeeeeek/electronic-wechat/events",
    "tagsUrl": "https://api.github.com/repos/geeeeeeeeek/electronic-wechat/tags",
    "languagesUrl": "https://api.github.com/repos/geeeeeeeeek/electronic-wechat/languages",
    "stargazersUrl": "https://api.github.com/repos/geeeeeeeeek/electronic-wechat/stargazers",
    "contributorsUrl": "https://api.github.com/repos/geeeeeeeeek/electronic-wechat/contributors",
    "subscribersUrl": "https://api.github.com/repos/geeeeeeeeek/electronic-wechat/subscribers",
    "subscriptionUrl": "https://api.github.com/repos/geeeeeeeeek/electronic-wechat/subscription",
    "mergesUrl": "https://api.github.com/repos/geeeeeeeeek/electronic-wechat/merges",
    "downloadsUrl": "https://api.github.com/repos/geeeeeeeeek/electronic-wechat/downloads",
    "deploymentsUrl": "https://api.github.com/repos/geeeeeeeeek/electronic-wechat/deployments",
    "createdAt": "2016-02-18T09:09:53.000Z",
    "updatedAt": "2017-05-04T19:21:49.000Z",
    "pushedAt": "2017-04-30T04:57:04.000Z",
    "gitUrl": "git://github.com/geeeeeeeeek/electronic-wechat.git",
    "sshUrl": "git@github.com:geeeeeeeeek/electronic-wechat.git",
    "cloneUrl": "https://github.com/geeeeeeeeek/electronic-wechat.git",
    "svnUrl": "https://github.com/geeeeeeeeek/electronic-wechat",
    "homepage": "",
    "size": 1095,
    "stargazersCount": 6904,
    "watchersCount": 6904,
    "language": "JavaScript",
    "hasIssues": true,
    "hasProjects": true,
    "hasDownloads": true,
    "hasWiki": true,
    "hasPages": false,
    "forksCount": 1189,
    "mirrorUrl": null,
    "openIssuesCount": 86,
    "openIssues": 86,
    "watchers": 6904,
    "defaultBranch": "master"
  },
  "source": {
    "id": 51994692,
    "name": "electronic-wechat",
    "fullName": "geeeeeeeeek/electronic-wechat",
    "owner": {
      "login": "geeeeeeeeek",
      "id": 7262715,
      "avatarUrl": "https://avatars2.githubusercontent.com/u/7262715?v=3",
      "gravatarId": "",
      "url": "https://api.github.com/users/geeeeeeeeek",
      "htmlUrl": "https://github.com/geeeeeeeeek",
      "followersUrl": "https://api.github.com/users/geeeeeeeeek/followers",
      "subscriptionsUrl": "https://api.github.com/users/geeeeeeeeek/subscriptions",
      "organizationsUrl": "https://api.github.com/users/geeeeeeeeek/orgs",
      "reposUrl": "https://api.github.com/users/geeeeeeeeek/repos",
      "receivedEventsUrl": "https://api.github.com/users/geeeeeeeeek/received_events",
      "type": "User"
    },
    "private": false,
    "htmlUrl": "https://github.com/geeeeeeeeek/electronic-wechat",
    "description": ":speech_balloon: A better WeChat on macOS and Linux. Built with Electron by Zhongyi Tong.",
    "fork": false,
    "url": "https://api.github.com/repos/geeeeeeeeek/electronic-wechat",
    "forksUrl": "https://api.github.com/repos/geeeeeeeeek/electronic-wechat/forks",
    "teamsUrl": "https://api.github.com/repos/geeeeeeeeek/electronic-wechat/teams",
    "hooksUrl": "https://api.github.com/repos/geeeeeeeeek/electronic-wechat/hooks",
    "eventsUrl": "https://api.github.com/repos/geeeeeeeeek/electronic-wechat/events",
    "tagsUrl": "https://api.github.com/repos/geeeeeeeeek/electronic-wechat/tags",
    "languagesUrl": "https://api.github.com/repos/geeeeeeeeek/electronic-wechat/languages",
    "stargazersUrl": "https://api.github.com/repos/geeeeeeeeek/electronic-wechat/stargazers",
    "contributorsUrl": "https://api.github.com/repos/geeeeeeeeek/electronic-wechat/contributors",
    "subscribersUrl": "https://api.github.com/repos/geeeeeeeeek/electronic-wechat/subscribers",
    "subscriptionUrl": "https://api.github.com/repos/geeeeeeeeek/electronic-wechat/subscription",
    "mergesUrl": "https://api.github.com/repos/geeeeeeeeek/electronic-wechat/merges",
    "downloadsUrl": "https://api.github.com/repos/geeeeeeeeek/electronic-wechat/downloads",
    "deploymentsUrl": "https://api.github.com/repos/geeeeeeeeek/electronic-wechat/deployments",
    "createdAt": "2016-02-18T09:09:53.000Z",
    "updatedAt": "2017-05-04T19:21:49.000Z",
    "pushedAt": "2017-04-30T04:57:04.000Z",
    "gitUrl": "git://github.com/geeeeeeeeek/electronic-wechat.git",
    "sshUrl": "git@github.com:geeeeeeeeek/electronic-wechat.git",
    "cloneUrl": "https://github.com/geeeeeeeeek/electronic-wechat.git",
    "svnUrl": "https://github.com/geeeeeeeeek/electronic-wechat",
    "homepage": "",
    "size": 1095,
    "stargazersCount": 6904,
    "watchersCount": 6904,
    "language": "JavaScript",
    "hasIssues": true,
    "hasProjects": true,
    "hasDownloads": true,
    "hasWiki": true,
    "hasPages": false,
    "forksCount": 1189,
    "mirrorUrl": null,
    "openIssuesCount": 86,
    "openIssues": 86,
    "watchers": 6904,
    "defaultBranch": "master"
  },
  "networkCount": 1189,
  "subscribersCount": 1,
  "status": 200,
  "lastFetchedAt": "2017-05-04T20:10:55.731Z"
}