{
  "filename": "xingoxu___ps4-wallpaper-helper.json",
  "id": 82311776,
  "name": "ps4-wallpaper-helper",
  "fullName": "xingoxu/ps4-wallpaper-helper",
  "owner": {
    "login": "xingoxu",
    "id": 8542907,
    "avatarUrl": "https://avatars0.githubusercontent.com/u/8542907?v=4",
    "gravatarId": "",
    "url": "https://api.github.com/users/xingoxu",
    "htmlUrl": "https://github.com/xingoxu",
    "followersUrl": "https://api.github.com/users/xingoxu/followers",
    "subscriptionsUrl": "https://api.github.com/users/xingoxu/subscriptions",
    "organizationsUrl": "https://api.github.com/users/xingoxu/orgs",
    "reposUrl": "https://api.github.com/users/xingoxu/repos",
    "receivedEventsUrl": "https://api.github.com/users/xingoxu/received_events",
    "type": "User"
  },
  "private": false,
  "htmlUrl": "https://github.com/xingoxu/ps4-wallpaper-helper",
  "description": "A helpful tool to change ps4 wallpaper",
  "fork": false,
  "url": "https://api.github.com/repos/xingoxu/ps4-wallpaper-helper",
  "forksUrl": "https://api.github.com/repos/xingoxu/ps4-wallpaper-helper/forks",
  "teamsUrl": "https://api.github.com/repos/xingoxu/ps4-wallpaper-helper/teams",
  "hooksUrl": "https://api.github.com/repos/xingoxu/ps4-wallpaper-helper/hooks",
  "eventsUrl": "https://api.github.com/repos/xingoxu/ps4-wallpaper-helper/events",
  "tagsUrl": "https://api.github.com/repos/xingoxu/ps4-wallpaper-helper/tags",
  "languagesUrl": "https://api.github.com/repos/xingoxu/ps4-wallpaper-helper/languages",
  "stargazersUrl": "https://api.github.com/repos/xingoxu/ps4-wallpaper-helper/stargazers",
  "contributorsUrl": "https://api.github.com/repos/xingoxu/ps4-wallpaper-helper/contributors",
  "subscribersUrl": "https://api.github.com/repos/xingoxu/ps4-wallpaper-helper/subscribers",
  "subscriptionUrl": "https://api.github.com/repos/xingoxu/ps4-wallpaper-helper/subscription",
  "mergesUrl": "https://api.github.com/repos/xingoxu/ps4-wallpaper-helper/merges",
  "downloadsUrl": "https://api.github.com/repos/xingoxu/ps4-wallpaper-helper/downloads",
  "deploymentsUrl": "https://api.github.com/repos/xingoxu/ps4-wallpaper-helper/deployments",
  "createdAt": "2017-02-17T15:43:25.000Z",
  "updatedAt": "2017-09-15T03:51:37.000Z",
  "pushedAt": "2017-03-10T12:24:28.000Z",
  "gitUrl": "git://github.com/xingoxu/ps4-wallpaper-helper.git",
  "sshUrl": "git@github.com:xingoxu/ps4-wallpaper-helper.git",
  "cloneUrl": "https://github.com/xingoxu/ps4-wallpaper-helper.git",
  "svnUrl": "https://github.com/xingoxu/ps4-wallpaper-helper",
  "homepage": "http://works.xingoxu.com/ps4helper/",
  "size": 20127,
  "stargazersCount": 9,
  "watchersCount": 9,
  "language": "JavaScript",
  "hasIssues": true,
  "hasProjects": true,
  "hasDownloads": true,
  "hasWiki": true,
  "hasPages": true,
  "forksCount": 0,
  "mirrorUrl": null,
  "archived": false,
  "openIssuesCount": 0,
  "openIssues": 0,
  "watchers": 9,
  "defaultBranch": "master",
  "permissions": {
    "admin": false,
    "push": false,
    "pull": true
  },
  "license": {
    "key": "mit",
    "name": "MIT License",
    "spdxId": "MIT",
    "url": "https://api.github.com/licenses/mit",
    "featured": true
  },
  "networkCount": 0,
  "subscribersCount": 2,
  "status": 200,
  "lastFetchedAt": "2017-10-23T22:11:33.904Z"
}